stnpy/__init__.py
stnpy/stn.py
stnpy-0.3.1.dist-info/METADATA
stnpy-0.3.1.dist-info/WHEEL
stnpy-0.3.1.dist-info/licenses/LICENSE
stnpy-0.3.1.dist-info/RECORD
