Metadata-Version: 2.3
Name: stnpy
Version: 0.3.1
Summary: Python port of R STN library
Project-URL: Homepage, https://github.com/runrunLauren/stnpy
Project-URL: Bug Tracker, https://github.com/runrunLauren/stnpy/issues
Author-email: Lauren Hayward <hayward.lauren111@gmail.com>
License-File: LICENSE
Classifier: License :: OSI Approved :: GNU General Public License v3 (GPLv3)
Classifier: Operating System :: OS Independent
Classifier: Programming Language :: Python :: 3
Requires-Python: >=3.7
Requires-Dist: networkx
Requires-Dist: numpy
Requires-Dist: pandas
Requires-Dist: statistics
